k8s_handle/__init__.py
k8s_handle/__main__.py
k8s_handle/config.py
k8s_handle/dictionary.py
k8s_handle/exceptions.py
k8s_handle/filesystem.py
k8s_handle/settings.py
k8s_handle/templating.py
k8s_handle/transforms.py
k8s_handle/k8s/__init__.py
k8s_handle/k8s/adapters.py
k8s_handle/k8s/api_extensions.py
k8s_handle/k8s/deprecation_checker.py
k8s_handle/k8s/diff.py
k8s_handle/k8s/mocks.py
k8s_handle/k8s/provisioner.py
k8s_handle/k8s/test_adapters.py
k8s_handle/k8s/test_deprecation_checker.py
k8s_handle/k8s/test_provisioner.py
k8s_handle/k8s/availability_checker/__init__.py
k8s_handle/k8s/availability_checker/checker.py
k8s_handle/k8s/availability_checker/mocks.py
k8s_handle/k8s/availability_checker/resource_getters.py
k8s_handle/k8s/availability_checker/test_availability_checker.py
k8s_handle/k8s/availability_checker/test_resource_getters.py
k8s_handle-0.16.0.data/data/requirements.txt
k8s_handle-0.16.0.dist-info/LICENSE
k8s_handle-0.16.0.dist-info/METADATA
k8s_handle-0.16.0.dist-info/WHEEL
k8s_handle-0.16.0.dist-info/entry_points.txt
k8s_handle-0.16.0.dist-info/top_level.txt
k8s_handle-0.16.0.dist-info/RECORD
