Metadata-Version: 2.1
Name: k8s-handle
Version: 0.16.0
Summary: Provisioning tool for Kubernetes apps
Home-page: http://github.com/2gis/k8s-handle
Author: Vadim Reyder
Author-email: vadim.reyder@gmail.com
License: Apache 2.0
Platform: UNKNOWN
License-File: LICENSE
Requires-Dist: requests (==2.28.1)
Requires-Dist: jinja2 (==3.1.2)
Requires-Dist: PyYAML (==5.4.1)
Requires-Dist: kubernetes (==24.2.0)
Requires-Dist: semver (==2.13.0)
